{"resolvedId":"D:/360MoveData/Users/28546/Desktop/VSCode/ts/life/node_modules/.store/lodash-es@4.17.21/node_modules/lodash-es/_mapCacheGet.js","transforms":[{"name":"vite:load-fallback","result":"import getMapData from './_getMapData.js';\n\n/**\n * Gets the map value for `key`.\n *\n * @private\n * @name get\n * @memberOf MapCache\n * @param {string} key The key of the value to get.\n * @returns {*} Returns the entry value.\n */\nfunction mapCacheGet(key) {\n  return getMapData(this, key).get(key);\n}\n\nexport default mapCacheGet;\n","start":1680879322613,"end":1680879322676}]}
